pynetft/NetFT.py
pynetft/__init__.py
pynetft-1.0.3.dist-info/LICENSE
pynetft-1.0.3.dist-info/METADATA
pynetft-1.0.3.dist-info/WHEEL
pynetft-1.0.3.dist-info/top_level.txt
pynetft-1.0.3.dist-info/RECORD
