Metadata-Version: 2.2
Name: pynetft
Version: 1.0.3
Summary: Python library for reading data from ATI Force/Torque sensors with Net F/T interface
Home-page: https://github.com/han-xudong/pyNetFT
Author: Xudong Han
License: MIT
Keywords: Net F/T,sensor
Classifier: Development Status :: 3 - Alpha
Classifier: Intended Audience :: Developers
Classifier: License :: OSI Approved :: MIT License
Classifier: Programming Language :: Python :: 3.10
Classifier: Topic :: Software Development :: Libraries :: Python Modules
Requires-Python: >=3.6
License-File: LICENSE
Dynamic: author
Dynamic: classifier
Dynamic: description
Dynamic: description-content-type
Dynamic: home-page
Dynamic: keywords
Dynamic: license
Dynamic: requires-python
Dynamic: summary
